model_field_list/__init__.py
model_field_list/fields.py
tests/__init__.py
tests/runtests.py
tests/testapp/__init__.py
tests/testapp/forms.py
tests/testapp/models.py
tests/testapp/urls.py
tests/testapp/urls_admin.py
tests/testapp/tests/__init__.py
tests/testapp/tests/test_admin.py
tests/testapp/tests/test_form.py
django_mflf-0.1.0.dist-info/LICENSE
django_mflf-0.1.0.dist-info/METADATA
django_mflf-0.1.0.dist-info/WHEEL
django_mflf-0.1.0.dist-info/top_level.txt
django_mflf-0.1.0.dist-info/RECORD
