Metadata-Version: 2.1
Name: django-mflf
Version: 0.1.0
Summary: Django model field list field
Home-page: https://github.com/andreynovikov/django-mlfl/tree/master
Author: Andrey Novikov
Author-email: novikov@gmail.com
License: MIT
Project-URL: Source, https://github.com/andreynovikov/django-mlfl/
Project-URL: Tracker, https://github.com/andreynovikov/django-mlfl/issues
Platform: UNKNOWN
Classifier: Development Status :: 4 - Beta
Classifier: Framework :: Django
Classifier: Programming Language :: Python
Classifier: Programming Language :: Python :: 2
Classifier: Programming Language :: Python :: 3
Classifier: License :: OSI Approved :: MIT License
Classifier: Operating System :: OS Independent
License-File: LICENSE
